common_utils/__init__.py
common_utils/version.py
common_utils/const/__init__.py
common_utils/const/message.py
common_utils/core/__init__.py
common_utils/core/aspect.py
common_utils/core/mapper.py
common_utils/core/scaffold.py
common_utils/core/unify_exception.py
common_utils/core/unify_response.py
common_utils/i18n/__init__.py
common_utils/utils/__init__.py
common_utils/utils/blueprint_util.py
common_utils/utils/config_util.py
common_utils/utils/dict_util.py
common_utils/utils/i18n_util.py
common_utils/utils/logger_util.py
common_utils/utils/string_util.py
common_utils/utils/tree_util.py
test_data/__init__.py
test_data/app/__init__.py
test_data/app/modules/__init__.py
test_data/app/modules/controller.py
test_data/app/modules/v1/__init__.py
test_data/app/modules/v1/controller.py
test_data/app/modules/v2/__init__.py
test_data/app/modules/v2/controller.py
common_flask_utils-0.1.5.dist-info/METADATA
common_flask_utils-0.1.5.dist-info/WHEEL
common_flask_utils-0.1.5.dist-info/top_level.txt
common_flask_utils-0.1.5.dist-info/RECORD
